mpyg321/BasePlayer.py
mpyg321/EventContext.py
mpyg321/MPyg123Player.py
mpyg321/MPyg321Player.py
mpyg321/MpygError.py
mpyg321/__init__.py
mpyg321/consts.py
mpyg321/mpyg321.py
mpyg321-2.2.2.dist-info/licenses/LICENSE
mpyg321-2.2.2.dist-info/METADATA
mpyg321-2.2.2.dist-info/WHEEL
mpyg321-2.2.2.dist-info/top_level.txt
mpyg321-2.2.2.dist-info/RECORD
