Metadata-Version: 2.4
Name: mpyg321
Version: 2.2.2
Summary: mpg321 wrapper for python - command line music player
Home-page: https://github.com/4br3mm0rd/mpyg321
Author: 4br3mm0rd
Author-email: 4br3mm0rd@gmail.com
Classifier: Programming Language :: Python :: 3
Classifier: License :: OSI Approved :: MIT License
Classifier: Operating System :: OS Independent
License-File: LICENSE
Requires-Dist: pexpect
Dynamic: author
Dynamic: author-email
Dynamic: classifier
Dynamic: description
Dynamic: description-content-type
Dynamic: home-page
Dynamic: license-file
Dynamic: requires-dist
Dynamic: summary
